tecan_od_analyzer/__init__.py
tecan_od_analyzer/__main__.py
tecan_od_analyzer/config.py
tecan_od_analyzer/tecan_od_analyzer.py
tecan_od_analyzer-0.1.6.dist-info/LICENSE
tecan_od_analyzer-0.1.6.dist-info/METADATA
tecan_od_analyzer-0.1.6.dist-info/WHEEL
tecan_od_analyzer-0.1.6.dist-info/dependency_links.txt
tecan_od_analyzer-0.1.6.dist-info/entry_points.txt
tecan_od_analyzer-0.1.6.dist-info/top_level.txt
tecan_od_analyzer-0.1.6.dist-info/RECORD
