Metadata-Version: 2.1
Name: tecan-od-analyzer
Version: 0.1.6
Summary: OD data handling for growth curve estimation and visualization of TECAN OD readings
Home-page: https://github.com/felixpacheco/AutoFlow-HTC/tree/felix_HTC
Author: Felix Pacheco Pastor
Author-email: fepac@biosustain.com
License: MIT
Platform: UNKNOWN
Classifier: Programming Language :: Python :: 3
Classifier: License :: OSI Approved :: MIT License
Classifier: Operating System :: OS Independent
Requires-Dist: numpy
Requires-Dist: matplotlib
Requires-Dist: pandas
Requires-Dist: datetime
Requires-Dist: argparse
Requires-Dist: path
Requires-Dist: xlsxwriter
Requires-Dist: seaborn
Requires-Dist: scipy
Requires-Dist: pycodestyle
Requires-Dist: sphinx
Requires-Dist: sphinx-rtd-theme
Requires-Dist: xlrd
